imgdl.py
setup.cfg
setup.py
img_dl.egg-info/PKG-INFO
img_dl.egg-info/SOURCES.txt
img_dl.egg-info/dependency_links.txt
img_dl.egg-info/entry_points.txt
img_dl.egg-info/requires.txt
img_dl.egg-info/top_level.txt