Metadata-Version: 1.1
Name: img-dl
Version: 0.1
Summary: CLI to download images
Home-page: https://github.com/ganesshkumar/imgdl
Author: Ganessh Kumar R P
Author-email: rpganesshkumar@gmail.com
License: UNKNOWN
Download-URL: https://github.com/ganesshkumar/imgdl/tarball/0.1
Keywords: image,downloader,imgur,image download
Platform: UNKNOWN
